timedelta_isoformat/__init__.py
timedelta_isoformat/py.typed
timedelta_isoformat-0.7.0.dist-info/LICENSE
timedelta_isoformat-0.7.0.dist-info/METADATA
timedelta_isoformat-0.7.0.dist-info/WHEEL
timedelta_isoformat-0.7.0.dist-info/top_level.txt
timedelta_isoformat-0.7.0.dist-info/RECORD
