Metadata-Version: 2.1
Name: timedelta-isoformat
Version: 0.7.0
Summary: Supplemental ISO8601 duration format support for datetime.timedelta
Author-email: James Addison <jay@jp-hosting.net>
License: AGPL-3.0-or-later
Project-URL: Homepage, https://pypi.org/project/timedelta-isoformat/
Project-URL: Source, https://github.com/jayaddison/timedelta-isoformat.git/
Classifier: License :: OSI Approved :: GNU Affero General Public License v3 or later (AGPLv3+)
Requires-Python: >=3.10
License-File: LICENSE
